foreverbull_cli/__init__.py
foreverbull_cli/output.py
foreverbull_cli/bull/__init__.py
foreverbull_cli/bull/backtest.py
foreverbull_cli/bull/cli.py
foreverbull_cli/env/__init__.py
foreverbull_cli/env/cli.py
foreverbull_cli/env/environment.py
foreverbull_cli-0.0.2503031831.dist-info/METADATA
foreverbull_cli-0.0.2503031831.dist-info/WHEEL
foreverbull_cli-0.0.2503031831.dist-info/entry_points.txt
foreverbull_cli-0.0.2503031831.dist-info/top_level.txt
foreverbull_cli-0.0.2503031831.dist-info/RECORD
