Metadata-Version: 2.2
Name: foreverbull_cli
Version: 0.0.2503031831
Summary: foreverbull
Author-email: Henrik Nilsson <henrik@lhjnilsson.com>
Requires-Dist: typer[all]<1.0.0,>=0.9.0
Requires-Dist: docker<8.0.0,>=7.0.0
